pynomics/__init__.py
pynomics/nomics_candle.py
pynomics-0.1.2.dist-info/WHEEL
pynomics-0.1.2.dist-info/METADATA
pynomics-0.1.2.dist-info/RECORD
